[{"name":"Mike Doe","email":"miked@example.com","avatar":{"sm":"\/img-sm.jpg","lg":"\/img-lg.jpg"},"_id":6},{"name":"Mike Doe","email":"miked@example.com","avatar":{"sm":"\/img-sm.jpg","lg":"\/img-lg.jpg"},"_id":1},{"name":"Mike Doe","email":"miked@example.com","avatar":{"sm":"\/img-sm.jpg","lg":"\/img-lg.jpg"},"_id":7},{"name":"Mike Doe","email":"miked@example.com","avatar":{"sm":"\/img-sm.jpg","lg":"\/img-lg.jpg"},"_id":2},{"model":"Q1","name":"ELETTROLUX AT400","ram":"128 gb","_id":11},{"name":"Mike Doe","email":"miked@example.com","avatar":{"sm":"\/img-sm.jpg","lg":"\/img-lg.jpg"},"_id":8},{"name":"Mike Doe","email":"miked@example.com","avatar":{"sm":"\/img-sm.jpg","lg":"\/img-lg.jpg"},"_id":5},{"name":"Mike Doe","email":"miked@example.com","avatar":{"sm":"\/img-sm.jpg","lg":"\/img-lg.jpg"},"_id":3},{"name":"Mike Doe","email":"miked@example.com","avatar":{"sm":"\/img-sm.jpg","lg":"\/img-lg.jpg"},"_id":4}]